pytorchcv/__init__.py
pytorchcv/model_provider.py
pytorchcv/models/__init__.py
pytorchcv/models/airnet.py
pytorchcv/models/airnext.py
pytorchcv/models/alexnet.py
pytorchcv/models/alphapose_coco.py
pytorchcv/models/bagnet.py
pytorchcv/models/bamresnet.py
pytorchcv/models/bisenet.py
pytorchcv/models/bninception.py
pytorchcv/models/cbamresnet.py
pytorchcv/models/centernet.py
pytorchcv/models/cgnet.py
pytorchcv/models/channelnet.py
pytorchcv/models/condensenet.py
pytorchcv/models/contextnet.py
pytorchcv/models/dabnet.py
pytorchcv/models/danet.py
pytorchcv/models/darknet.py
pytorchcv/models/darknet53.py
pytorchcv/models/darts.py
pytorchcv/models/deeplabv3.py
pytorchcv/models/densenet.py
pytorchcv/models/densenet_cifar.py
pytorchcv/models/diapreresnet.py
pytorchcv/models/diapreresnet_cifar.py
pytorchcv/models/diaresnet.py
pytorchcv/models/diaresnet_cifar.py
pytorchcv/models/dicenet.py
pytorchcv/models/diracnetv2.py
pytorchcv/models/dla.py
pytorchcv/models/dpn.py
pytorchcv/models/drn.py
pytorchcv/models/edanet.py
pytorchcv/models/efficientnet.py
pytorchcv/models/efficientnetedge.py
pytorchcv/models/enet.py
pytorchcv/models/erfnet.py
pytorchcv/models/esnet.py
pytorchcv/models/espcnet.py
pytorchcv/models/espnetv2.py
pytorchcv/models/fastscnn.py
pytorchcv/models/fastseresnet.py
pytorchcv/models/fbnet.py
pytorchcv/models/fcn8sd.py
pytorchcv/models/fdmobilenet.py
pytorchcv/models/fishnet.py
pytorchcv/models/fpenet.py
pytorchcv/models/fractalnet_cifar.py
pytorchcv/models/ghostnet.py
pytorchcv/models/hardnet.py
pytorchcv/models/hrnet.py
pytorchcv/models/ibnbresnet.py
pytorchcv/models/ibndensenet.py
pytorchcv/models/ibnresnet.py
pytorchcv/models/ibnresnext.py
pytorchcv/models/ibppose_coco.py
pytorchcv/models/icnet.py
pytorchcv/models/igcv3.py
pytorchcv/models/inceptionresnetv1.py
pytorchcv/models/inceptionresnetv2.py
pytorchcv/models/inceptionv3.py
pytorchcv/models/inceptionv4.py
pytorchcv/models/irevnet.py
pytorchcv/models/isqrtcovresnet.py
pytorchcv/models/jasper.py
pytorchcv-0.0.74.dist-info/licenses/LICENSE
pytorchcv-0.0.74.dist-info/METADATA
pytorchcv-0.0.74.dist-info/WHEEL
pytorchcv-0.0.74.dist-info/top_level.txt
pytorchcv-0.0.74.dist-info/RECORD
