Metadata-Version: 2.4
Name: pytorchcv
Version: 0.0.74
Summary: Computer vision models for PyTorch
Author-email: Oleg Sémery <osemery@gmail.com>
License-Expression: MIT
Project-URL: Homepage, https://github.com/osmr/pytorchcv
Keywords: machine-learning,deep-learning,neuralnetwork,image-classification,pytorch,imagenet,cifar,svhn,vgg,resnet,pyramidnet,diracnet,densenet,condensenet,wrn,drn,dpn,darknet,fishnet,espnetv2,xdensnet,squeezenet,squeezenext,shufflenet,menet,mobilenet,igcv3,mnasnet,darts,xception,inception,polynet,nasnet,pnasnet,ror,proxylessnas,dianet,efficientnet,mixnet,image-segmentation,voc,ade20k,cityscapes,coco,pspnet,deeplabv3,fcn
Classifier: Development Status :: 3 - Alpha
Classifier: Intended Audience :: Science/Research
Classifier: Operating System :: OS Independent
Classifier: Programming Language :: Python :: 3
Classifier: Topic :: Scientific/Engineering :: Image Recognition
Requires-Python: >=3.10
License-File: LICENSE
Requires-Dist: requests
Requires-Dist: numpy
Requires-Dist: torch
Requires-Dist: torchvision
Dynamic: license-file
